bad_setuptools_git_version.py
bad_setuptools_git_version-1.0.12.dist-info/LICENSE
bad_setuptools_git_version-1.0.12.dist-info/METADATA
bad_setuptools_git_version-1.0.12.dist-info/WHEEL
bad_setuptools_git_version-1.0.12.dist-info/entry_points.txt
bad_setuptools_git_version-1.0.12.dist-info/top_level.txt
bad_setuptools_git_version-1.0.12.dist-info/RECORD
