Metadata-Version: 2.1
Name: bad-setuptools-git-version
Version: 1.0.12
Summary: Automatically set package version using git tags.
Home-page: https://github.com/st7105/bad-setuptools-git-version
Author: st7105
Author-email: st7105@gmail.com
License: MIT
Keywords: setuptools git version-control
Platform: UNKNOWN
Classifier: Framework :: Setuptools Plugin
Classifier: Intended Audience :: Developers
Classifier: License :: OSI Approved :: MIT License
Classifier: Programming Language :: Python :: 2
Classifier: Programming Language :: Python :: 3
Classifier: Development Status :: 5 - Production/Stable
License-File: LICENSE
Requires-Dist: setuptools (>=8.0)
